temi_helpers/__init__.py
temi_helpers/api.py
temi_helpers/bip38.py
temi_helpers/keys.py
temi_helpers/utils.py
tests/__init__.py
tests/test_temi_helpers.py
temi_helpers-1.0.0.dist-info/METADATA
temi_helpers-1.0.0.dist-info/WHEEL
temi_helpers-1.0.0.dist-info/top_level.txt
temi_helpers-1.0.0.dist-info/RECORD
