Metadata-Version: 2.1
Name: temi-helpers
Version: 1.0.0
Summary: UNKNOWN
Home-page: UNKNOWN
Author: Junior Gantin
Author-email: nioperas06@gmail.com
License: UNKNOWN
Platform: UNKNOWN
Classifier: Programming Language :: Python :: 3
Classifier: License :: OSI Approved :: MIT License
Classifier: Operating System :: OS Independent
Requires-Dist: py-ecc
Requires-Dist: pycrypto
Requires-Dist: requests
Requires-Dist: scrypt
